cjm_transcription_plugin_whisper/__init__.py
cjm_transcription_plugin_whisper/_modidx.py
cjm_transcription_plugin_whisper/meta.py
cjm_transcription_plugin_whisper/plugin.py
cjm_transcription_plugin_whisper-0.0.11.dist-info/licenses/LICENSE
cjm_transcription_plugin_whisper-0.0.11.dist-info/METADATA
cjm_transcription_plugin_whisper-0.0.11.dist-info/WHEEL
cjm_transcription_plugin_whisper-0.0.11.dist-info/entry_points.txt
cjm_transcription_plugin_whisper-0.0.11.dist-info/top_level.txt
cjm_transcription_plugin_whisper-0.0.11.dist-info/RECORD
