Metadata-Version: 2.4
Name: cjm-transcription-plugin-whisper
Version: 0.0.11
Summary: OpenAI Whisper plugin for the cjm-transcription-plugin-system library - provides local speech-to-text transcription with configurable model selection and parameter control.
Home-page: https://github.com/cj-mills/cjm-transcription-plugin-whisper
Author: Christian J. Mills
Author-email: 9126128+cj-mills@users.noreply.github.com
License: Apache Software License 2.0
Keywords: nbdev jupyter notebook python
Classifier: Development Status :: 4 - Beta
Classifier: Intended Audience :: Developers
Classifier: Natural Language :: English
Classifier: Programming Language :: Python :: 3.11
Classifier: Programming Language :: Python :: 3.12
Classifier: License :: OSI Approved :: Apache Software License
Requires-Python: >=3.11
License-File: LICENSE
Requires-Dist: fastcore
Requires-Dist: pandas
Requires-Dist: cjm_transcription_plugin_system
Requires-Dist: openai-whisper
Requires-Dist: torch
Requires-Dist: numpy
Requires-Dist: soundfile
Requires-Dist: cjm_ffmpeg_utils
Provides-Extra: dev
Dynamic: author
Dynamic: author-email
Dynamic: classifier
Dynamic: description
Dynamic: description-content-type
Dynamic: home-page
Dynamic: keywords
Dynamic: license
Dynamic: license-file
Dynamic: provides-extra
Dynamic: requires-dist
Dynamic: requires-python
Dynamic: summary
